setup.py
django_pserver.egg-info/PKG-INFO
django_pserver.egg-info/SOURCES.txt
django_pserver.egg-info/dependency_links.txt
django_pserver.egg-info/top_level.txt
pserver/__init__.py
pserver/models.py
pserver/management/__init__.py
pserver/management/commands/__init__.py
pserver/management/commands/runserver.py