Metadata-Version: 1.0
Name: django-pserver
Version: 0.2
Summary: Django runserver replacement that reuses its listening socket on reload
Home-page: UNKNOWN
Author: Wil Tan
Author-email: wil@dready.org
License: MIT/X
Platform: UNKNOWN
Classifier: Development Status :: 4 - Beta
Classifier: Environment :: Web Environment
Classifier: Intended Audience :: Developers
Classifier: License :: OSI Approved :: MIT License
Classifier: Operating System :: MacOS :: MacOS X
Classifier: Operating System :: POSIX
Classifier: Programming Language :: Python
Classifier: Topic :: Internet
Classifier: Framework :: Django
